demo/__init__.py
demo/hello.py
coolstar3-0.0.0.dist-info/METADATA
coolstar3-0.0.0.dist-info/WHEEL
coolstar3-0.0.0.dist-info/top_level.txt
coolstar3-0.0.0.dist-info/RECORD
