Metadata-Version: 2.1
Name: coolstar3
Version: 0.0.0
Summary: A Python library for test.
Home-page: UNKNOWN
Author: seale
Author-email: seale@outlook.com
License: MIT
Platform: UNKNOWN
